brasil.gov.portal-2.1.1-py2.7-nspkg.pth
brasil/gov/portal/__init__.py
brasil/gov/portal/__init__.pyc
brasil/gov/portal/config.py
brasil/gov/portal/config.pyc
brasil/gov/portal/configure.zcml
brasil/gov/portal/dependencies.zcml
brasil/gov/portal/interfaces.py
brasil/gov/portal/interfaces.pyc
brasil/gov/portal/logger.py
brasil/gov/portal/logger.pyc
brasil/gov/portal/patches.py
brasil/gov/portal/patches.pyc
brasil/gov/portal/patches.zcml
brasil/gov/portal/profiles.zcml
brasil/gov/portal/setuphandlers.py
brasil/gov/portal/setuphandlers.pyc
brasil/gov/portal/testing.py
brasil/gov/portal/testing.pyc
brasil/gov/portal/utils.py
brasil/gov/portal/utils.pyc
brasil/gov/portal/browser/__init__.py
brasil/gov/portal/browser/__init__.pyc
brasil/gov/portal/browser/configure.zcml
brasil/gov/portal/browser/helper.py
brasil/gov/portal/browser/helper.pyc
brasil/gov/portal/browser/plonegovbr.png
brasil/gov/portal/browser/album/__init__.py
brasil/gov/portal/browser/album/__init__.pyc
brasil/gov/portal/browser/album/albuns.py
brasil/gov/portal/browser/album/albuns.pyc
brasil/gov/portal/browser/album/configure.zcml
brasil/gov/portal/browser/album/templates/galeria_de_albuns.pt
brasil/gov/portal/browser/album/templates/galeria_de_fotos.pt
brasil/gov/portal/browser/busca/__init__.py
brasil/gov/portal/browser/busca/__init__.pyc
brasil/gov/portal/browser/busca/busca.py
brasil/gov/portal/browser/busca/busca.pyc
brasil/gov/portal/browser/busca/configure.zcml
brasil/gov/portal/browser/busca/search.pt
brasil/gov/portal/browser/busca/searchbox.pt
brasil/gov/portal/browser/busca/searchbox.py
brasil/gov/portal/browser/busca/searchbox.pyc
brasil/gov/portal/browser/busca/updated_search.pt
brasil/gov/portal/browser/busca/js/search.js
brasil/gov/portal/browser/content/__init__.py
brasil/gov/portal/browser/content/__init__.pyc
brasil/gov/portal/browser/content/audio.py
brasil/gov/portal/browser/content/audio.pyc
brasil.gov.portal-2.1.1.dist-info/DESCRIPTION.rst
brasil.gov.portal-2.1.1.dist-info/METADATA
brasil.gov.portal-2.1.1.dist-info/RECORD
brasil.gov.portal-2.1.1.dist-info/WHEEL
brasil.gov.portal-2.1.1.dist-info/entry_points.txt
brasil.gov.portal-2.1.1.dist-info/metadata.json
brasil.gov.portal-2.1.1.dist-info/namespace_packages.txt
brasil.gov.portal-2.1.1.dist-info/top_level.txt
