Metadata-Version: 2.0
Name: brasil.gov.portal
Version: 2.1.1
Summary: Implementação Modelo da Identidade Digital de Governo
Home-page: https://github.com/plonegovbr/brasil.gov.portal
Author: PloneGov.BR
Author-email: gov@plone.org.br
License: GPLv2
Keywords: plone .gov.br identidade_digital egov
Platform: UNKNOWN
Classifier: Development Status :: 5 - Production/Stable
Classifier: Environment :: Web Environment
Classifier: Framework :: Plone
Classifier: Framework :: Plone :: 4.3
Classifier: Intended Audience :: Developers
Classifier: Intended Audience :: System Administrators
Classifier: License :: OSI Approved :: GNU General Public License v2 (GPLv2)
Classifier: Operating System :: OS Independent
Classifier: Programming Language :: JavaScript
Classifier: Programming Language :: Python
Classifier: Programming Language :: Python :: 2.7
Classifier: Topic :: Internet :: WWW/HTTP
Classifier: Topic :: Internet :: WWW/HTTP :: Dynamic Content
Classifier: Topic :: Multimedia
Classifier: Topic :: Software Development :: Libraries :: Python Modules
Provides-Extra: test
Provides-Extra: migration
Requires-Dist: AccessControl
Requires-Dist: Acquisition
Requires-Dist: brasil.gov.agenda
Requires-Dist: brasil.gov.barra
Requires-Dist: brasil.gov.portlets
Requires-Dist: brasil.gov.temas
Requires-Dist: brasil.gov.tiles
Requires-Dist: brasil.gov.vcge[dexterity]
Requires-Dist: collective.cover
Requires-Dist: collective.fingerpointing
Requires-Dist: collective.jsonmigrator
Requires-Dist: collective.lazysizes
Requires-Dist: collective.liveblog
Requires-Dist: collective.nitf
Requires-Dist: collective.polls
Requires-Dist: collective.upload
Requires-Dist: five.pt
Requires-Dist: lxml
Requires-Dist: plone.api
Requires-Dist: plone.app.content
Requires-Dist: plone.app.contenttypes
Requires-Dist: plone.app.controlpanel
Requires-Dist: plone.app.dexterity
Requires-Dist: plone.app.drafts
Requires-Dist: plone.app.layout
Requires-Dist: plone.app.registry
Requires-Dist: plone.app.search
Requires-Dist: plone.app.stagingbehavior
Requires-Dist: plone.app.theming
Requires-Dist: plone.app.viewletmanager
Requires-Dist: plone.autoform
Requires-Dist: plone.batching
Requires-Dist: plone.contentrules
Requires-Dist: plone.dexterity
Requires-Dist: plone.formwidget.namedfile
Requires-Dist: plone.i18n
Requires-Dist: plone.indexer
Requires-Dist: plone.memoize
Requires-Dist: plone.namedfile
Requires-Dist: plone.portlets
Requires-Dist: plone.protect (>=3.0.26)
Requires-Dist: plone.registry
Requires-Dist: plone.restapi
Requires-Dist: plone.supermodel
Requires-Dist: plone4.csrffixes
Requires-Dist: Products.CMFCore
Requires-Dist: Products.CMFDefault
Requires-Dist: Products.CMFPlone
Requires-Dist: Products.Doormat
Requires-Dist: Products.GenericSetup
Requires-Dist: Products.PloneFormGen
Requires-Dist: Products.PloneKeywordManager
Requires-Dist: Products.RedirectionTool
Requires-Dist: Products.TinyMCE
Requires-Dist: sc.contentrules.groupbydate
Requires-Dist: sc.contentrules.layout
Requires-Dist: sc.contentrules.metadata
Requires-Dist: sc.embedder
Requires-Dist: sc.photogallery
Requires-Dist: sc.social.like
Requires-Dist: setuptools
Requires-Dist: six
Requires-Dist: webcouturier.dropdownmenu
Requires-Dist: z3c.form
Requires-Dist: z3c.jbot
Requires-Dist: z3c.unconfigure
Requires-Dist: zope.component
Requires-Dist: zope.formlib
Requires-Dist: zope.i18nmessageid
Requires-Dist: zope.interface
Requires-Dist: zope.lifecycleevent
Requires-Dist: zope.schema
Requires-Dist: Zope2
Provides-Extra: migration
Requires-Dist: collective.jsonmigrator; extra == 'migration'
Requires-Dist: collective.transmogrifier; extra == 'migration'
Requires-Dist: plone.app.transmogrifier; extra == 'migration'
Requires-Dist: transmogrify.dexterity; extra == 'migration'
Provides-Extra: test
Requires-Dist: plone.app.robotframework[debug]; extra == 'test'
Requires-Dist: plone.app.testing[robot]; extra == 'test'
Requires-Dist: plone.browserlayer; extra == 'test'
Requires-Dist: plone.folder; extra == 'test'
Requires-Dist: plone.testing; extra == 'test'
Requires-Dist: plonetheme.sunburst; extra == 'test'
Requires-Dist: Products.GenericSetup; extra == 'test'
Requires-Dist: robotframework-wavelibrary; extra == 'test'
Requires-Dist: robotsuite; extra == 'test'
Requires-Dist: transaction; extra == 'test'
Requires-Dist: zope.publisher; extra == 'test'
Requires-Dist: zope.viewlet; extra == 'test'
